redux/__init__.py
redux/framework.py
redux/websocket.py
redux_python-0.1.0.dist-info/METADATA
redux_python-0.1.0.dist-info/RECORD
redux_python-0.1.0.dist-info/WHEEL
redux_python-0.1.0.dist-info/top_level.txt
