Metadata-Version: 2.1
Name: redux-python
Version: 0.1.0
Summary: UNKNOWN
Home-page: https://github.com/xdusongwei/redux-python
Author: songwei
Author-email: songwei@songwei.io
License: UNKNOWN
Platform: UNKNOWN
Classifier: Development Status :: 4 - Beta
Classifier: Intended Audience :: Developers
Classifier: Programming Language :: Python :: 3
Requires-Dist: websockets
